{
  "largestKillingSpree": "Largest Killing Spree",
  "largestMultiKill": "Largest Multi Kill",
  "timeCCingOthers": "Crowd Control Score",
  "totalDamageDealtToChampions": "Damage to Champions",
  "physicalDamageDealtToChampions": "Physical Damage to Champions",
  "magicDamageDealtToChampions": "Magical Damage to Champions",
  "trueDamageDealtToChampions": "True Damage to Champions",
  "totalDamageDealt": "Total Damage",
  "physicalDamageDealt": "Physical Damage",
  "magicDamageDealt": "Magical Damage",
  "trueDamageDealt": "True Damage",
  "largestCriticalStrike": "Largest Crit",
  "damageDealtToTurrets": "Damage to Turrets",
  "damageDealtToObjectives": "Damage to Objectives",
  "totalHeal": "Damage Healed",
  "totalDamageTaken": "Damage Taken",
  "physicalDamageTaken": "Physical Damage Taken",
  "magicalDamageTaken": "Magical Damage Taken",
  "trueDamageTaken": "True Damage Taken",
  "damageSelfMitigated": "Damage Mitigated",
  "visionScore": "Vision Score",
  "wardsPlaced": "Wards Placed",
  "wardsKilled": "Wards Killed",
  "visionWardsBoughtInGame": "Control Wards Bought",
  "goldEarned": "Gold Earned",
  "goldSpent": "Gold Spent",
  "totalMinionsKilled": "Creep Score",
  "neutralMinionsKilled": "Jungle Monsters Killed",
  "neutralMinionsKilledTeamJungle": "Team Jungle Monsters Killed",
  "neutralMinionsKilledEnemyJungle": "Enemy Jungle Monsters Killed",
  "turretKills": "Towers Destroyed",
  "inhibitorKills": "Inhibitors Destroyed",
  "null": "null"
}